<?xml version="1.0" encoding="utf-8"?>
<SoundBanksInfo Platform="Windows" BasePlatform="Windows" SchemaVersion="12" SoundbankVersion="140">
	<RootPaths>
		<ProjectRoot>X:\Coursework\AUD312\Assignment\Wwise Project\</ProjectRoot>
		<SourceFilesRoot>X:\Coursework\AUD312\Assignment\Wwise Project\.cache\Windows\</SourceFilesRoot>
		<SoundBanksRoot>X:\Coursework\AUD312\Assignment\Wwise Project\GeneratedSoundBanks\Windows\</SoundBanksRoot>
		<ExternalSourcesInputFile></ExternalSourcesInputFile>
		<ExternalSourcesOutputRoot>X:\Coursework\AUD312\Assignment\Wwise Project\GeneratedSoundBanks\Windows</ExternalSourcesOutputRoot>
	</RootPaths>
	<DialogueEvents/>
	<StreamedFiles/>
	<MediaFilesNotInAnyBank/>
	<SoundBanks>
		<SoundBank Id="1355168291" Language="SFX" Hash="632156442">
			<ObjectPath>Init</ObjectPath>
			<ShortName>Init</ShortName>
			<Path>Init.bnk</Path>
			<GameParameters>
				<GameParameter Id="1042517418" Name="WindIntensity" ObjectPath="\Game Parameters\Default Work Unit\Ambience\WindIntensity"/>
			</GameParameters>
			<StateGroups>
				<StateGroup Id="2558423223" Name="BoxState" ObjectPath="\States\Default Work Unit\Music\BoxState" GUID="{54C47F18-4243-4FC9-91BF-C729E3ADD7FB}">
					<States>
						<State Id="748895195" Name="None" ObjectPath="\States\Default Work Unit\Music\BoxState\None" GUID="{8717C20B-71BC-4F3A-81F3-657F374E86E2}"/>
						<State Id="2060468149" Name="BoxHeld" ObjectPath="\States\Default Work Unit\Music\BoxState\BoxHeld" GUID="{DA60839B-344D-45C3-9134-81D0EECBFB60}"/>
					</States>
				</StateGroup>
				<StateGroup Id="3156432362" Name="WorldKeysEnabled" ObjectPath="\States\Default Work Unit\Interactions\WorldKeysEnabled" GUID="{3D9DDB20-C64A-41E8-AB49-B2F23F8A3894}">
					<States>
						<State Id="748895195" Name="None" ObjectPath="\States\Default Work Unit\Interactions\WorldKeysEnabled\None" GUID="{736387CA-55D4-40F8-9E17-9A74C12A83DA}"/>
						<State Id="4174102348" Name="Enabled" ObjectPath="\States\Default Work Unit\Interactions\WorldKeysEnabled\Enabled" GUID="{878828F1-1468-4F40-A5E9-4D39491D6B11}"/>
					</States>
				</StateGroup>
			</StateGroups>
		</SoundBank>
		<SoundBank Id="3161908922" Language="SFX" Hash="1385714969">
			<ObjectPath>\SoundBanks\Default Work Unit\Main</ObjectPath>
			<ShortName>Main</ShortName>
			<Path>Main.bnk</Path>
			<IncludedEvents>
				<Event Id="829164566" Name="BoxAmbiencePlay" ObjectPath="\Events\Default Work Unit\SFX\Box\BoxAmbiencePlay" MaxAttenuation="20.000000" DurationType="Infinite">
					<IncludedMemoryFiles>
						<File Id="117760886" Language="SFX">
							<ShortName>music_boat_cube.wav</ShortName>
							<Path>SFX\music_boat_cube_D79FB2B7.wem</Path>
						</File>
					</IncludedMemoryFiles>
				</Event>
				<Event Id="3810078911" Name="BoxDrop" ObjectPath="\Events\Default Work Unit\SFX\Box\BoxDrop" MaxAttenuation="0.000000" DurationType="OneShot" DurationMin="0.000000" DurationMax="0.000000">
					<ActionTrigger>
						<ActionTriggerEntry Id="556308635" Name="BoxDropStinger" ObjectPath="\Triggers\Default Work Unit\BoxDropStinger"/>
					</ActionTrigger>
				</Event>
				<Event Id="241339208" Name="BoxDropCue" ObjectPath="\Events\Default Work Unit\Music\Cue Events\Stingers\BoxDropCue" MaxAttenuation="0.000000" DurationType="OneShot" DurationMin="0.000000" DurationMax="0.000000">
					<ActionSetState>
						<ActionSetStateEntry Id="748895195" Name="None" ObjectPath="\States\Default Work Unit\Music\BoxState\None"/>
					</ActionSetState>
				</Event>
				<Event Id="2671589300" Name="BoxPickup" ObjectPath="\Events\Default Work Unit\SFX\Box\BoxPickup" MaxAttenuation="0.000000" DurationType="OneShot" DurationMin="0.000000" DurationMax="0.000000">
					<ActionTrigger>
						<ActionTriggerEntry Id="3525814506" Name="BoxPickupStinger" ObjectPath="\Triggers\Default Work Unit\BoxPickupStinger"/>
					</ActionTrigger>
				</Event>
				<Event Id="4115829741" Name="BoxPickupCue" ObjectPath="\Events\Default Work Unit\Music\Cue Events\Stingers\BoxPickupCue" MaxAttenuation="0.000000" DurationType="OneShot" DurationMin="0.000000" DurationMax="0.000000">
					<ActionSetState>
						<ActionSetStateEntry Id="2060468149" Name="BoxHeld" ObjectPath="\States\Default Work Unit\Music\BoxState\BoxHeld"/>
					</ActionSetState>
				</Event>
				<Event Id="3547374172" Name="BoxSegmentDownCue" ObjectPath="\Events\Default Work Unit\Music\Cue Events\Stingers\BoxSegmentDownCue" MaxAttenuation="0.000000" DurationType="OneShot" DurationMin="0.000000" DurationMax="0.000000">
					<ActionSetState>
						<ActionSetStateEntry Id="3791155954" Name="Muted" ObjectPath="\States\Default Work Unit\Music\BoxOpeningStingerState\Muted"/>
					</ActionSetState>
				</Event>
				<Event Id="1360996149" Name="BoxSegmentUpCue" ObjectPath="\Events\Default Work Unit\Music\Cue Events\Stingers\BoxSegmentUpCue" MaxAttenuation="0.000000" DurationType="OneShot" DurationMin="0.000000" DurationMax="0.000000">
					<ActionSetState>
						<ActionSetStateEntry Id="748895195" Name="None" ObjectPath="\States\Default Work Unit\Music\BoxOpeningStingerState\None"/>
					</ActionSetState>
				</Event>
				<Event Id="1721219483" Name="EnterIndoors" ObjectPath="\Events\Default Work Unit\Level\Room\EnterIndoors" MaxAttenuation="0.000000" DurationType="OneShot" DurationMin="0.000000" DurationMax="0.000000">
					<ActionSetState>
						<ActionSetStateEntry Id="748895195" Name="None" ObjectPath="\States\Default Work Unit\Rooms\Room_Type\None"/>
					</ActionSetState>
				</Event>
				<Event Id="1113956849" Name="EnterIndoorsTunnel" ObjectPath="\Events\Default Work Unit\Level\Room\EnterIndoorsTunnel" MaxAttenuation="0.000000" DurationType="OneShot" DurationMin="0.000000" DurationMax="0.000000">
					<ActionSetState>
						<ActionSetStateEntry Id="3059984139" Name="Tunnel" ObjectPath="\States\Default Work Unit\Rooms\Room_Type\Tunnel"/>
					</ActionSetState>
				</Event>
				<Event Id="3070671186" Name="EnterOutdoors" ObjectPath="\Events\Default Work Unit\Level\Room\EnterOutdoors" MaxAttenuation="0.000000" DurationType="OneShot" DurationMin="0.000000" DurationMax="0.000000">
					<ActionSetState>
						<ActionSetStateEntry Id="2730119150" Name="Outdoors" ObjectPath="\States\Default Work Unit\Rooms\Room_Type\Outdoors"/>
					</ActionSetState>
				</Event>
				<Event Id="2811934447" Name="EnterTunnel" ObjectPath="\Events\Default Work Unit\Level\Room\EnterTunnel" MaxAttenuation="0.000000" DurationType="OneShot" DurationMin="0.000000" DurationMax="0.000000">
					<ActionSetState>
						<ActionSetStateEntry Id="3059984139" Name="Tunnel" ObjectPath="\States\Default Work Unit\Rooms\Room_Type\Tunnel"/>
					</ActionSetState>
				</Event>
				<Event Id="4039405217" Name="FootstepPlay" ObjectPath="\Events\Default Work Unit\SFX\Footstep\FootstepPlay" DurationType="OneShot" DurationMin="0.164984" DurationMax="1.135410">
					<IncludedMemoryFiles>
						<File Id="3342881" Language="SFX">
							<ShortName>sfx_footstep_toe_concrete_03.wav</ShortName>
							<Path>SFX\sfx_footstep_toe_concrete_03_10C4C929.wem</Path>
						</File>
						<File Id="13459026" Language="SFX">
							<ShortName>sfx_footstep_toe_cloth_04.wav</ShortName>
							<Path>SFX\sfx_footstep_toe_cloth_04_10C4C929.wem</Path>
						</File>
						<File Id="16215833" Language="SFX">
							<ShortName>sfx_footstep_heel_grass_02.wav</ShortName>
							<Path>SFX\sfx_footstep_heel_grass_02_10C4C929.wem</Path>
						</File>
						<File Id="39568453" Language="SFX">
							<ShortName>sfx_footstep_toe_gravel_02.wav</ShortName>
							<Path>SFX\sfx_footstep_toe_gravel_02_10C4C929.wem</Path>
						</File>
						<File Id="40909859" Language="SFX">
							<ShortName>sfx_footstep_heel_concrete_01.wav</ShortName>
							<Path>SFX\sfx_footstep_heel_concrete_01_10C4C929.wem</Path>
						</File>
						<File Id="56514661" Language="SFX">
							<ShortName>sfx_footstep_heel_glass_04.wav</ShortName>
							<Path>SFX\sfx_footstep_heel_glass_04_10C4C929.wem</Path>
						</File>
						<File Id="71636352" Language="SFX">
							<ShortName>sfx_footstep_heel_concrete_03.wav</ShortName>
							<Path>SFX\sfx_footstep_heel_concrete_03_10C4C929.wem</Path>
						</File>
						<File Id="75070834" Language="SFX">
							<ShortName>sfx_footstep_heel_gravel_02.wav</ShortName>
							<Path>SFX\sfx_footstep_heel_gravel_02_10C4C929.wem</Path>
						</File>
						<File Id="86169055" Language="SFX">
							<ShortName>sfx_footstep_toe_glass_01.wav</ShortName>
							<Path>SFX\sfx_footstep_toe_glass_01_10C4C929.wem</Path>
						</File>
						<File Id="87916936" Language="SFX">
							<ShortName>sfx_footstep_toe_concrete_01.wav</ShortName>
							<Path>SFX\sfx_footstep_toe_concrete_01_10C4C929.wem</Path>
						</File>
						<File Id="95916828" Language="SFX">
							<ShortName>sfx_footstep_heel_concrete_02.wav</ShortName>
							<Path>SFX\sfx_footstep_heel_concrete_02_10C4C929.wem</Path>
						</File>
						<File Id="101588032" Language="SFX">
							<ShortName>sfx_footstep_heel_cloth_02.wav</ShortName>
							<Path>SFX\sfx_footstep_heel_cloth_02_10C4C929.wem</Path>
						</File>
						<File Id="152547260" Language="SFX">
							<ShortName>sfx_footstep_toe_grass_03.wav</ShortName>
							<Path>SFX\sfx_footstep_toe_grass_03_10C4C929.wem</Path>
						</File>
						<File Id="159164666" Language="SFX">
							<ShortName>sfx_footstep_toe_metal_04.wav</ShortName>
							<Path>SFX\sfx_footstep_toe_metal_04_10C4C929.wem</Path>
						</File>
						<File Id="172730326" Language="SFX">
							<ShortName>sfx_footstep_heel_wood_03.wav</ShortName>
							<Path>SFX\sfx_footstep_heel_wood_03_10C4C929.wem</Path>
						</File>
						<File Id="182318414" Language="SFX">
							<ShortName>sfx_footstep_toe_metal_03.wav</ShortName>
							<Path>SFX\sfx_footstep_toe_metal_03_10C4C929.wem</Path>
						</File>
						<File Id="229562338" Language="SFX">
							<ShortName>sfx_footstep_toe_wood_02.wav</ShortName>
							<Path>SFX\sfx_footstep_toe_wood_02_10C4C929.wem</Path>
						</File>
						<File Id="232315487" Language="SFX">
							<ShortName>sfx_footstep_heel_wood_01.wav</ShortName>
							<Path>SFX\sfx_footstep_heel_wood_01_10C4C929.wem</Path>
						</File>
						<File Id="244810268" Language="SFX">
							<ShortName>sfx_creak_01.wav</ShortName>
							<Path>SFX\sfx_creak_01_10C4C929.wem</Path>
						</File>
						<File Id="248964196" Language="SFX">
							<ShortName>sfx_footstep_heel_glass_02.wav</ShortName>
							<Path>SFX\sfx_footstep_heel_glass_02_10C4C929.wem</Path>
						</File>
						<File Id="259592201" Language="SFX">
							<ShortName>sfx_footstep_toe_glass_03.wav</ShortName>
							<Path>SFX\sfx_footstep_toe_glass_03_10C4C929.wem</Path>
						</File>
						<File Id="290479511" Language="SFX">
							<ShortName>sfx_footstep_heel_metal_01.wav</ShortName>
							<Path>SFX\sfx_footstep_heel_metal_01_10C4C929.wem</Path>
						</File>
						<File Id="307567616" Language="SFX">
							<ShortName>sfx_footstep_heel_grass_03.wav</ShortName>
							<Path>SFX\sfx_footstep_heel_grass_03_10C4C929.wem</Path>
						</File>
						<File Id="327118990" Language="SFX">
							<ShortName>sfx_footstep_heel_wood_04.wav</ShortName>
							<Path>SFX\sfx_footstep_heel_wood_04_10C4C929.wem</Path>
						</File>
						<File Id="382858474" Language="SFX">
							<ShortName>sfx_footstep_toe_wood_01.wav</ShortName>
							<Path>SFX\sfx_footstep_toe_wood_01_10C4C929.wem</Path>
						</File>
						<File Id="387958526" Language="SFX">
							<ShortName>sfx_footstep_heel_cloth_03.wav</ShortName>
							<Path>SFX\sfx_footstep_heel_cloth_03_10C4C929.wem</Path>
						</File>
						<File Id="411723609" Language="SFX">
							<ShortName>sfx_footstep_heel_cloth_04.wav</ShortName>
							<Path>SFX\sfx_footstep_heel_cloth_04_10C4C929.wem</Path>
						</File>
						<File Id="424800491" Language="SFX">
							<ShortName>sfx_footstep_toe_cloth_01.wav</ShortName>
							<Path>SFX\sfx_footstep_toe_cloth_01_10C4C929.wem</Path>
						</File>
						<File Id="430779212" Language="SFX">
							<ShortName>sfx_creak_03.wav</ShortName>
							<Path>SFX\sfx_creak_03_10C4C929.wem</Path>
						</File>
						<File Id="433346874" Language="SFX">
							<ShortName>sfx_footstep_heel_grass_01.wav</ShortName>
							<Path>SFX\sfx_footstep_heel_grass_01_10C4C929.wem</Path>
						</File>
						<File Id="433560062" Language="SFX">
							<ShortName>sfx_creak_02.wav</ShortName>
							<Path>SFX\sfx_creak_02_10C4C929.wem</Path>
						</File>
						<File Id="469003920" Language="SFX">
							<ShortName>sfx_footstep_toe_metal_01.wav</ShortName>
							<Path>SFX\sfx_footstep_toe_metal_01_10C4C929.wem</Path>
						</File>
						<File Id="472897795" Language="SFX">
							<ShortName>sfx_footstep_toe_gravel_01.wav</ShortName>
							<Path>SFX\sfx_footstep_toe_gravel_01_10C4C929.wem</Path>
						</File>
						<File Id="489199625" Language="SFX">
							<ShortName>sfx_footstep_heel_glass_01.wav</ShortName>
							<Path>SFX\sfx_footstep_heel_glass_01_10C4C929.wem</Path>
						</File>
						<File Id="499273913" Language="SFX">
							<ShortName>sfx_footstep_heel_glass_03.wav</ShortName>
							<Path>SFX\sfx_footstep_heel_glass_03_10C4C929.wem</Path>
						</File>
						<File Id="518684506" Language="SFX">
							<ShortName>sfx_footstep_toe_wood_03.wav</ShortName>
							<Path>SFX\sfx_footstep_toe_wood_03_10C4C929.wem</Path>
						</File>
						<File Id="562976292" Language="SFX">
							<ShortName>sfx_footstep_heel_gravel_04.wav</ShortName>
							<Path>SFX\sfx_footstep_heel_gravel_04_10C4C929.wem</Path>
						</File>
						<File Id="564781057" Language="SFX">
							<ShortName>sfx_footstep_toe_concrete_04.wav</ShortName>
							<Path>SFX\sfx_footstep_toe_concrete_04_10C4C929.wem</Path>
						</File>
						<File Id="575773855" Language="SFX">
							<ShortName>sfx_footstep_toe_wood_04.wav</ShortName>
							<Path>SFX\sfx_footstep_toe_wood_04_10C4C929.wem</Path>
						</File>
						<File Id="578292259" Language="SFX">
							<ShortName>sfx_footstep_toe_grass_01.wav</ShortName>
							<Path>SFX\sfx_footstep_toe_grass_01_10C4C929.wem</Path>
						</File>
						<File Id="580354750" Language="SFX">
							<ShortName>sfx_footstep_heel_metal_02.wav</ShortName>
							<Path>SFX\sfx_footstep_heel_metal_02_10C4C929.wem</Path>
						</File>
						<File Id="581596431" Language="SFX">
							<ShortName>sfx_footstep_toe_cloth_03.wav</ShortName>
							<Path>SFX\sfx_footstep_toe_cloth_03_10C4C929.wem</Path>
						</File>
						<File Id="633135558" Language="SFX">
							<ShortName>sfx_footstep_heel_wood_02.wav</ShortName>
							<Path>SFX\sfx_footstep_heel_wood_02_10C4C929.wem</Path>
						</File>
						<File Id="647506356" Language="SFX">
							<ShortName>sfx_footstep_heel_metal_04.wav</ShortName>
							<Path>SFX\sfx_footstep_heel_metal_04_10C4C929.wem</Path>
						</File>
						<File Id="690254642" Language="SFX">
							<ShortName>sfx_footstep_heel_gravel_03.wav</ShortName>
							<Path>SFX\sfx_footstep_heel_gravel_03_10C4C929.wem</Path>
						</File>
						<File Id="728214015" Language="SFX">
							<ShortName>sfx_footstep_heel_concrete_04.wav</ShortName>
							<Path>SFX\sfx_footstep_heel_concrete_04_10C4C929.wem</Path>
						</File>
						<File Id="740430124" Language="SFX">
							<ShortName>sfx_footstep_toe_metal_02.wav</ShortName>
							<Path>SFX\sfx_footstep_toe_metal_02_10C4C929.wem</Path>
						</File>
						<File Id="755488523" Language="SFX">
							<ShortName>sfx_footstep_toe_gravel_04.wav</ShortName>
							<Path>SFX\sfx_footstep_toe_gravel_04_10C4C929.wem</Path>
						</File>
						<File Id="780591092" Language="SFX">
							<ShortName>sfx_footstep_toe_gravel_03.wav</ShortName>
							<Path>SFX\sfx_footstep_toe_gravel_03_10C4C929.wem</Path>
						</File>
						<File Id="791132644" Language="SFX">
							<ShortName>sfx_footstep_heel_grass_04.wav</ShortName>
							<Path>SFX\sfx_footstep_heel_grass_04_10C4C929.wem</Path>
						</File>
						<File Id="908824202" Language="SFX">
							<ShortName>sfx_footstep_heel_cloth_01.wav</ShortName>
							<Path>SFX\sfx_footstep_heel_cloth_01_10C4C929.wem</Path>
						</File>
						<File Id="921881356" Language="SFX">
							<ShortName>sfx_footstep_toe_glass_04.wav</ShortName>
							<Path>SFX\sfx_footstep_toe_glass_04_10C4C929.wem</Path>
						</File>
						<File Id="924280309" Language="SFX">
							<ShortName>sfx_footstep_toe_grass_04.wav</ShortName>
							<Path>SFX\sfx_footstep_toe_grass_04_10C4C929.wem</Path>
						</File>
						<File Id="924549011" Language="SFX">
							<ShortName>sfx_footstep_toe_glass_02.wav</ShortName>
							<Path>SFX\sfx_footstep_toe_glass_02_10C4C929.wem</Path>
						</File>
						<File Id="943315901" Language="SFX">
							<ShortName>sfx_footstep_heel_gravel_01.wav</ShortName>
							<Path>SFX\sfx_footstep_heel_gravel_01_10C4C929.wem</Path>
						</File>
						<File Id="974338589" Language="SFX">
							<ShortName>sfx_footstep_toe_grass_02.wav</ShortName>
							<Path>SFX\sfx_footstep_toe_grass_02_10C4C929.wem</Path>
						</File>
						<File Id="1007454756" Language="SFX">
							<ShortName>sfx_footstep_toe_cloth_02.wav</ShortName>
							<Path>SFX\sfx_footstep_toe_cloth_02_10C4C929.wem</Path>
						</File>
						<File Id="1008776830" Language="SFX">
							<ShortName>sfx_footstep_toe_concrete_02.wav</ShortName>
							<Path>SFX\sfx_footstep_toe_concrete_02_10C4C929.wem</Path>
						</File>
						<File Id="1067817721" Language="SFX">
							<ShortName>sfx_footstep_heel_metal_03.wav</ShortName>
							<Path>SFX\sfx_footstep_heel_metal_03_10C4C929.wem</Path>
						</File>
					</IncludedMemoryFiles>
					<DefaultSwitchValue>{F6050909-D3FC-4A0B-B34B-CED6BB085408}</DefaultSwitchValue>
					<SwitchContainers>
						<SwitchContainer SwitchValue="{F6050909-D3FC-4A0B-B34B-CED6BB085408}">
							<Media>
								<File Id="3342881"/>
								<File Id="40909859"/>
								<File Id="71636352"/>
								<File Id="87916936"/>
								<File Id="95916828"/>
								<File Id="564781057"/>
								<File Id="728214015"/>
								<File Id="1008776830"/>
							</Media>
						</SwitchContainer>
						<SwitchContainer SwitchValue="{05C16097-8E3C-4946-A103-D61957EBA3B4}">
							<Media>
								<File Id="16215833"/>
								<File Id="152547260"/>
								<File Id="307567616"/>
								<File Id="433346874"/>
								<File Id="578292259"/>
								<File Id="791132644"/>
								<File Id="924280309"/>
								<File Id="974338589"/>
							</Media>
						</SwitchContainer>
						<SwitchContainer SwitchValue="{0DA1C6E4-91C6-467A-A8DC-8C1509316FB7}">
							<Media>
								<File Id="39568453"/>
								<File Id="75070834"/>
								<File Id="472897795"/>
								<File Id="562976292"/>
								<File Id="690254642"/>
								<File Id="755488523"/>
								<File Id="780591092"/>
								<File Id="943315901"/>
							</Media>
						</SwitchContainer>
						<SwitchContainer SwitchValue="{C9ED3BA4-F979-4932-8E3B-C493E6E05FEA}">
							<Media>
								<File Id="13459026"/>
								<File Id="101588032"/>
								<File Id="387958526"/>
								<File Id="411723609"/>
								<File Id="424800491"/>
								<File Id="581596431"/>
								<File Id="908824202"/>
								<File Id="1007454756"/>
							</Media>
						</SwitchContainer>
						<SwitchContainer SwitchValue="{C9ED3BA4-F979-4932-8E3B-C493E6E05FEA}">
							<Media>
								<File Id="244810268"/>
								<File Id="430779212"/>
								<File Id="433560062"/>
							</Media>
						</SwitchContainer>
						<SwitchContainer SwitchValue="{1338EB15-8A56-4726-ACE6-2940071E11BB}">
							<Media>
								<File Id="172730326"/>
								<File Id="229562338"/>
								<File Id="232315487"/>
								<File Id="327118990"/>
								<File Id="382858474"/>
								<File Id="518684506"/>
								<File Id="575773855"/>
								<File Id="633135558"/>
							</Media>
						</SwitchContainer>
						<SwitchContainer SwitchValue="{1338EB15-8A56-4726-ACE6-2940071E11BB}">
							<Media>
								<File Id="244810268"/>
								<File Id="430779212"/>
								<File Id="433560062"/>
							</Media>
						</SwitchContainer>
						<SwitchContainer SwitchValue="{DAC7E030-D095-4C82-90E9-955164EC2CA0}">
							<Media>
								<File Id="159164666"/>
								<File Id="182318414"/>
								<File Id="290479511"/>
								<File Id="469003920"/>
								<File Id="580354750"/>
								<File Id="647506356"/>
								<File Id="740430124"/>
								<File Id="1067817721"/>
							</Media>
						</SwitchContainer>
						<SwitchContainer SwitchValue="{6076D9FF-D4F2-4936-AD82-036303957D93}">
							<Media>
								<File Id="56514661"/>
								<File Id="86169055"/>
								<File Id="248964196"/>
								<File Id="259592201"/>
								<File Id="489199625"/>
								<File Id="499273913"/>
								<File Id="921881356"/>
								<File Id="924549011"/>
							</Media>
						</SwitchContainer>
					</SwitchContainers>
					<ActionPostEvent>
						<ActionPostEventEntry Id="4288247056" Name="FootstepVampCooldown" ObjectPath="\Events\Default Work Unit\SFX\Footstep\FootstepVampCooldown"/>
					</ActionPostEvent>
				</Event>
				<Event Id="4288247056" Name="FootstepVampCooldown" ObjectPath="\Events\Default Work Unit\SFX\Footstep\FootstepVampCooldown" MaxAttenuation="0.000000" DurationType="OneShot" DurationMin="0.000000" DurationMax="0.000000"/>
				<Event Id="561183332" Name="HarpoonAmbiencePlay" ObjectPath="\Events\Default Work Unit\SFX\Harpoon\HarpoonAmbiencePlay" MaxAttenuation="20.000000" DurationType="Infinite">
					<IncludedMemoryFiles>
						<File Id="154507780" Language="SFX">
							<ShortName>music_boat_intensebass_4.wav</ShortName>
							<Path>SFX\music_boat_intensebass_4_D79FB2B7.wem</Path>
						</File>
						<File Id="250696590" Language="SFX">
							<ShortName>music_boat_distortbass.wav</ShortName>
							<Path>SFX\music_boat_distortbass_D79FB2B7.wem</Path>
						</File>
						<File Id="268973021" Language="SFX">
							<ShortName>music_boat_intensebass_3.wav</ShortName>
							<Path>SFX\music_boat_intensebass_3_D79FB2B7.wem</Path>
						</File>
						<File Id="718091025" Language="SFX">
							<ShortName>music_boat_intensebass_1.wav</ShortName>
							<Path>SFX\music_boat_intensebass_1_D79FB2B7.wem</Path>
						</File>
						<File Id="981262424" Language="SFX">
							<ShortName>music_boat_intensebass_2.wav</ShortName>
							<Path>SFX\music_boat_intensebass_2_D79FB2B7.wem</Path>
						</File>
					</IncludedMemoryFiles>
				</Event>
				<Event Id="3333733726" Name="HarpoonAmbienceStop" ObjectPath="\Events\Default Work Unit\SFX\Harpoon\HarpoonAmbienceStop" MaxAttenuation="0.000000" DurationType="OneShot" DurationMin="0.000000" DurationMax="0.000000"/>
				<Event Id="2421633396" Name="HarpoonFireReturn" ObjectPath="\Events\Default Work Unit\SFX\Harpoon\HarpoonFireReturn" DurationType="OneShot" DurationMin="3.700000" DurationMax="3.700000">
					<IncludedMemoryFiles>
						<File Id="117884843" Language="SFX">
							<ShortName>sfx_harpoon_shoot_reel_air.wav</ShortName>
							<Path>SFX\sfx_harpoon_shoot_reel_air_10C4C929.wem</Path>
						</File>
						<File Id="570316296" Language="SFX">
							<ShortName>sfx_harpoon_shoot_reel_chain.wav</ShortName>
							<Path>SFX\sfx_harpoon_shoot_reel_chain_10C4C929.wem</Path>
						</File>
						<File Id="604781409" Language="SFX">
							<ShortName>sfx_harpoon_shoot_a.wav</ShortName>
							<Path>SFX\sfx_harpoon_shoot_a_10C4C929.wem</Path>
						</File>
						<File Id="845357093" Language="SFX">
							<ShortName>sfx_harpoon_shoot_b.wav</ShortName>
							<Path>SFX\sfx_harpoon_shoot_b_10C4C929.wem</Path>
						</File>
					</IncludedMemoryFiles>
					<DefaultSwitchValue>{4B9FB557-3308-4BF4-9ECA-486659E8A285}</DefaultSwitchValue>
					<SwitchContainers>
						<SwitchContainer SwitchValue="{4B9FB557-3308-4BF4-9ECA-486659E8A285}">
							<Media>
								<File Id="604781409"/>
							</Media>
						</SwitchContainer>
						<SwitchContainer SwitchValue="{4B9FB557-3308-4BF4-9ECA-486659E8A285}">
							<Media>
								<File Id="845357093"/>
							</Media>
						</SwitchContainer>
					</SwitchContainers>
					<ActionSetState>
						<ActionSetStateEntry Id="2378879461" Name="HasFired" ObjectPath="\States\Default Work Unit\Interactions\HarpoonFired\HasFired"/>
					</ActionSetState>
				</Event>
				<Event Id="2837856117" Name="HarpoonGrabSuccess" ObjectPath="\Events\Default Work Unit\SFX\Harpoon\HarpoonGrabSuccess" DurationType="OneShot" DurationMin="2.138458" DurationMax="2.138458">
					<IncludedMemoryFiles>
						<File Id="128127013" Language="SFX">
							<ShortName>sfx_harpoon_shoot_reel_heavychain.wav</ShortName>
							<Path>SFX\sfx_harpoon_shoot_reel_heavychain_10C4C929.wem</Path>
						</File>
						<File Id="965794218" Language="SFX">
							<ShortName>sfx_harpoon_shoot_reel_heavyair.wav</ShortName>
							<Path>SFX\sfx_harpoon_shoot_reel_heavyair_10C4C929.wem</Path>
						</File>
					</IncludedMemoryFiles>
				</Event>
				<Event Id="2867011390" Name="HarpoonPickup" ObjectPath="\Events\Default Work Unit\SFX\Harpoon\HarpoonPickup" MaxAttenuation="0.000000" DurationType="OneShot" DurationMin="0.000000" DurationMax="0.000000">
					<ActionSetState>
						<ActionSetStateEntry Id="515864255" Name="HarpoonHeld" ObjectPath="\States\Default Work Unit\Interactions\HarpoonState\HarpoonHeld"/>
					</ActionSetState>
				</Event>
				<Event Id="757170495" Name="HarpoonReceived" ObjectPath="\Events\Default Work Unit\SFX\Harpoon\HarpoonReceived" MaxAttenuation="0.000000" DurationType="OneShot" DurationMin="0.000000" DurationMax="0.000000">
					<ActionSetState>
						<ActionSetStateEntry Id="748895195" Name="None" ObjectPath="\States\Default Work Unit\Interactions\HarpoonFired\None"/>
					</ActionSetState>
				</Event>
				<Event Id="3672941687" Name="LevelBigRoomReveal" ObjectPath="\Events\Default Work Unit\Level\Beats\LevelBigRoomReveal" MaxAttenuation="0.000000" DurationType="OneShot" DurationMin="0.000000" DurationMax="0.000000">
					<ActionPostEvent>
						<ActionPostEventEntry Id="3070671186" Name="EnterOutdoors" ObjectPath="\Events\Default Work Unit\Level\Room\EnterOutdoors"/>
					</ActionPostEvent>
				</Event>
				<Event Id="3372421815" Name="LevelStart" ObjectPath="\Events\Default Work Unit\Level\Beats\LevelStart" MaxAttenuation="0.000000" DurationType="OneShot" DurationMin="0.000000" DurationMax="0.000000">
					<ActionPostEvent>
						<ActionPostEventEntry Id="1122283870" Name="MusicStart" ObjectPath="\Events\Default Work Unit\Music\MusicStart"/>
						<ActionPostEventEntry Id="1661560854" Name="SFXStart" ObjectPath="\Events\Default Work Unit\SFX\SFXStart"/>
					</ActionPostEvent>
				</Event>
				<Event Id="1122283870" Name="MusicStart" ObjectPath="\Events\Default Work Unit\Music\MusicStart" DurationType="Infinite">
					<IncludedMemoryFiles>
						<File Id="47062023" Language="SFX">
							<ShortName>music_boat_kicksnare_1.wav</ShortName>
							<Path>SFX\music_boat_kicksnare_1_D79FB2B7.wem</Path>
						</File>
						<File Id="78535861" Language="SFX">
							<ShortName>music_boat_fantasychords_chorus.wav</ShortName>
							<Path>SFX\music_boat_fantasychords_chorus_D79FB2B7.wem</Path>
						</File>
						<File Id="83555245" Language="SFX">
							<ShortName>music_boat_boxdrop_1.wav</ShortName>
							<Path>SFX\music_boat_boxdrop_1_D79FB2B7.wem</Path>
						</File>
						<File Id="154507780" Language="SFX">
							<ShortName>music_boat_intensebass_4.wav</ShortName>
							<Path>SFX\music_boat_intensebass_4_D79FB2B7.wem</Path>
						</File>
						<File Id="229936893" Language="SFX">
							<ShortName>music_boat_kicksnare_chorus.wav</ShortName>
							<Path>SFX\music_boat_kicksnare_chorus_D79FB2B7.wem</Path>
						</File>
						<File Id="268973021" Language="SFX">
							<ShortName>music_boat_intensebass_3.wav</ShortName>
							<Path>SFX\music_boat_intensebass_3_D79FB2B7.wem</Path>
						</File>
						<File Id="348634579" Language="SFX">
							<ShortName>music_boat_blob_1.wav</ShortName>
							<Path>SFX\music_boat_blob_1_D79FB2B7.wem</Path>
						</File>
						<File Id="421281352" Language="SFX">
							<ShortName>music_boat_alberti_chorus_1.wav</ShortName>
							<Path>SFX\music_boat_alberti_chorus_1_D79FB2B7.wem</Path>
						</File>
						<File Id="441135101" Language="SFX">
							<ShortName>music_boat_bassline_1.wav</ShortName>
							<Path>SFX\music_boat_bassline_1_D79FB2B7.wem</Path>
						</File>
						<File Id="500195945" Language="SFX">
							<ShortName>music_boat_aggressivekicksnare_1.wav</ShortName>
							<Path>SFX\music_boat_aggressivekicksnare_1_D79FB2B7.wem</Path>
						</File>
						<File Id="544473361" Language="SFX">
							<ShortName>music_boat_vamp_1.wav</ShortName>
							<Path>SFX\music_boat_vamp_1_D79FB2B7.wem</Path>
						</File>
						<File Id="552614302" Language="SFX">
							<ShortName>music_boat_kicksnare_2.wav</ShortName>
							<Path>SFX\music_boat_kicksnare_2_D79FB2B7.wem</Path>
						</File>
						<File Id="621386646" Language="SFX">
							<ShortName>music_boat_aggressivekicksnare_2.wav</ShortName>
							<Path>SFX\music_boat_aggressivekicksnare_2_D79FB2B7.wem</Path>
						</File>
						<File Id="664813967" Language="SFX">
							<ShortName>music_boat_intensebass_chorus.wav</ShortName>
							<Path>SFX\music_boat_intensebass_chorus_D79FB2B7.wem</Path>
						</File>
						<File Id="670314713" Language="SFX">
							<ShortName>music_boat_boxpickup_1.wav</ShortName>
							<Path>SFX\music_boat_boxpickup_1_D79FB2B7.wem</Path>
						</File>
						<File Id="683807433" Language="SFX">
							<ShortName>music_boat_boxholding_1.wav</ShortName>
							<Path>SFX\music_boat_boxholding_1_D79FB2B7.wem</Path>
						</File>
						<File Id="718091025" Language="SFX">
							<ShortName>music_boat_intensebass_1.wav</ShortName>
							<Path>SFX\music_boat_intensebass_1_D79FB2B7.wem</Path>
						</File>
						<File Id="727411136" Language="SFX">
							<ShortName>music_boat_intensevamp_chorus_1.wav</ShortName>
							<Path>SFX\music_boat_intensevamp_chorus_1_D79FB2B7.wem</Path>
						</File>
						<File Id="791546088" Language="SFX">
							<ShortName>music_boat_boxholding_2.wav</ShortName>
							<Path>SFX\music_boat_boxholding_2_D79FB2B7.wem</Path>
						</File>
						<File Id="813604374" Language="SFX">
							<ShortName>music_boat_boxholding_3.wav</ShortName>
							<Path>SFX\music_boat_boxholding_3_D79FB2B7.wem</Path>
						</File>
						<File Id="837806047" Language="SFX">
							<ShortName>music_boat_aggressivekicksnare_chorus.wav</ShortName>
							<Path>SFX\music_boat_aggressivekicksnare_chorus_D79FB2B7.wem</Path>
						</File>
						<File Id="843600277" Language="SFX">
							<ShortName>music_boat_countermelody_1.wav</ShortName>
							<Path>SFX\music_boat_countermelody_1_D79FB2B7.wem</Path>
						</File>
						<File Id="847061519" Language="SFX">
							<ShortName>music_boat_alberti_1.wav</ShortName>
							<Path>SFX\music_boat_alberti_1_D79FB2B7.wem</Path>
						</File>
						<File Id="853425278" Language="SFX">
							<ShortName>music_boat_countermelody_2.wav</ShortName>
							<Path>SFX\music_boat_countermelody_2_D79FB2B7.wem</Path>
						</File>
						<File Id="913142023" Language="SFX">
							<ShortName>music_boat_vamp_chorus_1.wav</ShortName>
							<Path>SFX\music_boat_vamp_chorus_1_D79FB2B7.wem</Path>
						</File>
						<File Id="931555717" Language="SFX">
							<ShortName>music_boat_intensealberti_chorus_1.wav</ShortName>
							<Path>SFX\music_boat_intensealberti_chorus_1_D79FB2B7.wem</Path>
						</File>
						<File Id="966247712" Language="SFX">
							<ShortName>music_boat_hats_chorus.wav</ShortName>
							<Path>SFX\music_boat_hats_chorus_D79FB2B7.wem</Path>
						</File>
						<File Id="981262424" Language="SFX">
							<ShortName>music_boat_intensebass_2.wav</ShortName>
							<Path>SFX\music_boat_intensebass_2_D79FB2B7.wem</Path>
						</File>
						<File Id="1046108589" Language="SFX">
							<ShortName>music_boat_hats_1.wav</ShortName>
							<Path>SFX\music_boat_hats_1_D79FB2B7.wem</Path>
						</File>
						<File Id="1046767504" Language="SFX">
							<ShortName>music_boat_counterblob_1.wav</ShortName>
							<Path>SFX\music_boat_counterblob_1_D79FB2B7.wem</Path>
						</File>
						<File Id="1048122433" Language="SFX">
							<ShortName>music_boat_melody_1.wav</ShortName>
							<Path>SFX\music_boat_melody_1_D79FB2B7.wem</Path>
						</File>
						<File Id="1049002355" Language="SFX">
							<ShortName>music_boat_fantasychords_1.wav</ShortName>
							<Path>SFX\music_boat_fantasychords_1_D79FB2B7.wem</Path>
						</File>
					</IncludedMemoryFiles>
				</Event>
				<Event Id="1661560854" Name="SFXStart" ObjectPath="\Events\Default Work Unit\SFX\SFXStart" DurationType="Infinite">
					<IncludedMemoryFiles>
						<File Id="200076591" Language="SFX">
							<ShortName>sfx_pinknoise.wav</ShortName>
							<Path>SFX\sfx_pinknoise_10C4C929.wem</Path>
						</File>
					</IncludedMemoryFiles>
					<ActionSetState>
						<ActionSetStateEntry Id="4174102348" Name="Enabled" ObjectPath="\States\Default Work Unit\Interactions\WorldKeysEnabled\Enabled"/>
					</ActionSetState>
				</Event>
				<Event Id="157353963" Name="StepOffBed" ObjectPath="\Events\Default Work Unit\SFX\Bed\StepOffBed" MaxAttenuation="10.000000" DurationType="OneShot" DurationMin="0.341723" DurationMax="0.675119">
					<IncludedMemoryFiles>
						<File Id="244810268" Language="SFX">
							<ShortName>sfx_creak_01.wav</ShortName>
							<Path>SFX\sfx_creak_01_10C4C929.wem</Path>
						</File>
						<File Id="430779212" Language="SFX">
							<ShortName>sfx_creak_03.wav</ShortName>
							<Path>SFX\sfx_creak_03_10C4C929.wem</Path>
						</File>
						<File Id="433560062" Language="SFX">
							<ShortName>sfx_creak_02.wav</ShortName>
							<Path>SFX\sfx_creak_02_10C4C929.wem</Path>
						</File>
					</IncludedMemoryFiles>
				</Event>
				<Event Id="135348085" Name="StepOnBed" ObjectPath="\Events\Default Work Unit\SFX\Bed\StepOnBed" MaxAttenuation="10.000000" DurationType="OneShot" DurationMin="1.384785" DurationMax="1.384785">
					<IncludedMemoryFiles>
						<File Id="1002766583" Language="SFX">
							<ShortName>sfx_bed_compress.wav</ShortName>
							<Path>SFX\sfx_bed_compress_10C4C929.wem</Path>
						</File>
					</IncludedMemoryFiles>
				</Event>
				<Event Id="1973723167" Name="TreeAmbiencePlay" ObjectPath="\Events\Default Work Unit\SFX\TreeAmbiencePlay" MaxAttenuation="15.000000" DurationType="Infinite">
					<IncludedMemoryFiles>
						<File Id="43452734" Language="SFX">
							<ShortName>sfx_treewind_rustle.wav</ShortName>
							<Path>SFX\sfx_treewind_rustle_D79FB2B7.wem</Path>
						</File>
						<File Id="200076591" Language="SFX">
							<ShortName>sfx_pinknoise.wav</ShortName>
							<Path>SFX\sfx_pinknoise_10C4C929.wem</Path>
						</File>
					</IncludedMemoryFiles>
				</Event>
				<Event Id="3724088773" Name="WorldKey_A5" ObjectPath="\Events\Default Work Unit\SFX\WorldKeys\WorldKey_A5" DurationType="OneShot" DurationMin="0.150000" DurationMax="0.150000">
					<IncludedMemoryFiles>
						<File Id="238751466" Language="SFX">
							<ShortName>sfx_worldkeys_fmaj_a5.wav</ShortName>
							<Path>SFX\sfx_worldkeys_fmaj_a5_10C4C929.wem</Path>
						</File>
					</IncludedMemoryFiles>
				</Event>
				<Event Id="3724088774" Name="WorldKey_A6" ObjectPath="\Events\Default Work Unit\SFX\WorldKeys\WorldKey_A6" DurationType="OneShot" DurationMin="0.150000" DurationMax="0.150000">
					<IncludedMemoryFiles>
						<File Id="834793506" Language="SFX">
							<ShortName>sfx_worldkeys_fmaj_a6.wav</ShortName>
							<Path>SFX\sfx_worldkeys_fmaj_a6_10C4C929.wem</Path>
						</File>
					</IncludedMemoryFiles>
				</Event>
				<Event Id="3774421660" Name="WorldKey_B5" ObjectPath="\Events\Default Work Unit\SFX\WorldKeys\WorldKey_B5" DurationType="OneShot" DurationMin="0.150000" DurationMax="0.150000">
					<IncludedMemoryFiles>
						<File Id="729801942" Language="SFX">
							<ShortName>sfx_worldkeys_fmaj_b5.wav</ShortName>
							<Path>SFX\sfx_worldkeys_fmaj_b5_10C4C929.wem</Path>
						</File>
					</IncludedMemoryFiles>
				</Event>
				<Event Id="3774421663" Name="WorldKey_B6" ObjectPath="\Events\Default Work Unit\SFX\WorldKeys\WorldKey_B6" DurationType="OneShot" DurationMin="0.150000" DurationMax="0.150000">
					<IncludedMemoryFiles>
						<File Id="357251596" Language="SFX">
							<ShortName>sfx_worldkeys_fmaj_b6.wav</ShortName>
							<Path>SFX\sfx_worldkeys_fmaj_b6_10C4C929.wem</Path>
						</File>
					</IncludedMemoryFiles>
				</Event>
				<Event Id="3757644067" Name="WorldKey_C5" ObjectPath="\Events\Default Work Unit\SFX\WorldKeys\WorldKey_C5" DurationType="OneShot" DurationMin="0.150000" DurationMax="0.150000">
					<IncludedMemoryFiles>
						<File Id="537943496" Language="SFX">
							<ShortName>sfx_worldkeys_fmaj_c5.wav</ShortName>
							<Path>SFX\sfx_worldkeys_fmaj_c5_10C4C929.wem</Path>
						</File>
					</IncludedMemoryFiles>
				</Event>
				<Event Id="3757644064" Name="WorldKey_C6" ObjectPath="\Events\Default Work Unit\SFX\WorldKeys\WorldKey_C6" DurationType="OneShot" DurationMin="0.150000" DurationMax="0.150000">
					<IncludedMemoryFiles>
						<File Id="290204500" Language="SFX">
							<ShortName>sfx_worldkeys_fmaj_c6.wav</ShortName>
							<Path>SFX\sfx_worldkeys_fmaj_c6_10C4C929.wem</Path>
						</File>
					</IncludedMemoryFiles>
				</Event>
				<Event Id="3807976954" Name="WorldKey_D5" ObjectPath="\Events\Default Work Unit\SFX\WorldKeys\WorldKey_D5" DurationType="OneShot" DurationMin="0.150000" DurationMax="0.150000">
					<IncludedMemoryFiles>
						<File Id="459803870" Language="SFX">
							<ShortName>sfx_worldkeys_fmaj_d5.wav</ShortName>
							<Path>SFX\sfx_worldkeys_fmaj_d5_10C4C929.wem</Path>
						</File>
					</IncludedMemoryFiles>
				</Event>
				<Event Id="3807976953" Name="WorldKey_D6" ObjectPath="\Events\Default Work Unit\SFX\WorldKeys\WorldKey_D6" DurationType="OneShot" DurationMin="0.150000" DurationMax="0.150000">
					<IncludedMemoryFiles>
						<File Id="874895148" Language="SFX">
							<ShortName>sfx_worldkeys_fmaj_d6.wav</ShortName>
							<Path>SFX\sfx_worldkeys_fmaj_d6_10C4C929.wem</Path>
						</File>
					</IncludedMemoryFiles>
				</Event>
				<Event Id="3791199241" Name="WorldKey_E5" ObjectPath="\Events\Default Work Unit\SFX\WorldKeys\WorldKey_E5" DurationType="OneShot" DurationMin="0.150000" DurationMax="0.150000">
					<IncludedMemoryFiles>
						<File Id="929290808" Language="SFX">
							<ShortName>sfx_worldkeys_fmaj_e5.wav</ShortName>
							<Path>SFX\sfx_worldkeys_fmaj_e5_10C4C929.wem</Path>
						</File>
					</IncludedMemoryFiles>
				</Event>
				<Event Id="3791199242" Name="WorldKey_E6" ObjectPath="\Events\Default Work Unit\SFX\WorldKeys\WorldKey_E6" DurationType="OneShot" DurationMin="0.150000" DurationMax="0.150000">
					<IncludedMemoryFiles>
						<File Id="634912013" Language="SFX">
							<ShortName>sfx_worldkeys_fmaj_e6.wav</ShortName>
							<Path>SFX\sfx_worldkeys_fmaj_e6_10C4C929.wem</Path>
						</File>
					</IncludedMemoryFiles>
				</Event>
				<Event Id="3841532097" Name="WorldKey_F4" ObjectPath="\Events\Default Work Unit\SFX\WorldKeys\WorldKey_F4" DurationType="OneShot" DurationMin="0.150000" DurationMax="0.150000">
					<IncludedMemoryFiles>
						<File Id="626233591" Language="SFX">
							<ShortName>sfx_worldkeys_fmaj_f4.wav</ShortName>
							<Path>SFX\sfx_worldkeys_fmaj_f4_10C4C929.wem</Path>
						</File>
					</IncludedMemoryFiles>
				</Event>
				<Event Id="3841532096" Name="WorldKey_F5" ObjectPath="\Events\Default Work Unit\SFX\WorldKeys\WorldKey_F5" DurationType="OneShot" DurationMin="0.150000" DurationMax="0.150000">
					<IncludedMemoryFiles>
						<File Id="620271118" Language="SFX">
							<ShortName>sfx_worldkeys_fmaj_f5.wav</ShortName>
							<Path>SFX\sfx_worldkeys_fmaj_f5_10C4C929.wem</Path>
						</File>
					</IncludedMemoryFiles>
				</Event>
				<Event Id="3841532099" Name="WorldKey_F6" ObjectPath="\Events\Default Work Unit\SFX\WorldKeys\WorldKey_F6" DurationType="OneShot" DurationMin="0.150000" DurationMax="0.150000">
					<IncludedMemoryFiles>
						<File Id="779589527" Language="SFX">
							<ShortName>sfx_worldkeys_fmaj_f6.wav</ShortName>
							<Path>SFX\sfx_worldkeys_fmaj_f6_10C4C929.wem</Path>
						</File>
					</IncludedMemoryFiles>
				</Event>
				<Event Id="3824754518" Name="WorldKey_G4" ObjectPath="\Events\Default Work Unit\SFX\WorldKeys\WorldKey_G4" DurationType="OneShot" DurationMin="0.150000" DurationMax="0.150000">
					<IncludedMemoryFiles>
						<File Id="1043027253" Language="SFX">
							<ShortName>sfx_worldkeys_fmaj_g4.wav</ShortName>
							<Path>SFX\sfx_worldkeys_fmaj_g4_10C4C929.wem</Path>
						</File>
					</IncludedMemoryFiles>
				</Event>
				<Event Id="3824754519" Name="WorldKey_G5" ObjectPath="\Events\Default Work Unit\SFX\WorldKeys\WorldKey_G5" DurationType="OneShot" DurationMin="0.150000" DurationMax="0.150000">
					<IncludedMemoryFiles>
						<File Id="700459820" Language="SFX">
							<ShortName>sfx_worldkeys_fmaj_g5.wav</ShortName>
							<Path>SFX\sfx_worldkeys_fmaj_g5_10C4C929.wem</Path>
						</File>
					</IncludedMemoryFiles>
				</Event>
			</IncludedEvents>
			<GameParameters>
				<GameParameter Id="244091178" Name="VampCooldown" ObjectPath="\Game Parameters\Default Work Unit\Footstep\VampCooldown"/>
				<GameParameter Id="3587782899" Name="FootstepWeight" ObjectPath="\Game Parameters\Default Work Unit\Footstep\FootstepWeight"/>
				<GameParameter Id="3762319931" Name="BoxSegment" ObjectPath="\Game Parameters\Default Work Unit\Interactions\BoxSegment"/>
			</GameParameters>
			<StateGroups>
				<StateGroup Id="379189110" Name="HarpoonFired" ObjectPath="\States\Default Work Unit\Interactions\HarpoonFired" GUID="{73735AFF-F44D-45C6-97A0-D344484F219B}">
					<States>
						<State Id="748895195" Name="None" ObjectPath="\States\Default Work Unit\Interactions\HarpoonFired\None" GUID="{4B9FB557-3308-4BF4-9ECA-486659E8A285}"/>
						<State Id="2378879461" Name="HasFired" ObjectPath="\States\Default Work Unit\Interactions\HarpoonFired\HasFired" GUID="{47EC628F-C044-4F20-B62D-21B04E2A5BD3}"/>
					</States>
				</StateGroup>
				<StateGroup Id="515864255" Name="HarpoonHeld" ObjectPath="\States\Default Work Unit\Interactions\HarpoonState\HarpoonHeld" GUID="{801A23EA-9585-4040-B632-EAA67C533806}">
					<States/>
				</StateGroup>
				<StateGroup Id="748895195" Name="None" ObjectPath="\States\Default Work Unit\Interactions\HarpoonFired\None" GUID="{4B9FB557-3308-4BF4-9ECA-486659E8A285}">
					<States/>
				</StateGroup>
				<StateGroup Id="1363879777" Name="HarpoonState" ObjectPath="\States\Default Work Unit\Interactions\HarpoonState" GUID="{B3B48258-D25F-4931-8CC3-FC069EC03744}">
					<States>
						<State Id="748895195" Name="None" ObjectPath="\States\Default Work Unit\Interactions\HarpoonState\None" GUID="{C588DF7E-B70F-4E2A-9BBA-8BDBBAA976D1}"/>
						<State Id="515864255" Name="HarpoonHeld" ObjectPath="\States\Default Work Unit\Interactions\HarpoonState\HarpoonHeld" GUID="{801A23EA-9585-4040-B632-EAA67C533806}"/>
					</States>
				</StateGroup>
				<StateGroup Id="1941896134" Name="Room_C" ObjectPath="\States\Default Work Unit\Rooms\Room_C" GUID="{0F51F7A7-DA4E-491F-97F6-EE94B00CB2F9}">
					<States>
						<State Id="748895195" Name="None" ObjectPath="\States\Default Work Unit\Rooms\Room_C\None" GUID="{19496866-5461-430E-A457-14160955E205}"/>
						<State Id="2764605217" Name="Passed" ObjectPath="\States\Default Work Unit\Rooms\Room_C\Passed" GUID="{D06C60D8-9FF5-4474-897E-D7DD6F79A673}"/>
					</States>
				</StateGroup>
				<StateGroup Id="1941896135" Name="Room_B" ObjectPath="\States\Default Work Unit\Rooms\Room_B" GUID="{0F28CB9D-8E69-4152-BC69-50EE91E39FC8}">
					<States>
						<State Id="748895195" Name="None" ObjectPath="\States\Default Work Unit\Rooms\Room_B\None" GUID="{E604430D-8069-4F71-9B77-F5EA3F936052}"/>
						<State Id="2764605217" Name="Passed" ObjectPath="\States\Default Work Unit\Rooms\Room_B\Passed" GUID="{5B851545-24BC-4022-8588-F9946FE0E763}"/>
					</States>
				</StateGroup>
				<StateGroup Id="2060468149" Name="BoxHeld" ObjectPath="\States\Default Work Unit\Music\BoxState\BoxHeld" GUID="{DA60839B-344D-45C3-9134-81D0EECBFB60}">
					<States/>
				</StateGroup>
				<StateGroup Id="2378879461" Name="HasFired" ObjectPath="\States\Default Work Unit\Interactions\HarpoonFired\HasFired" GUID="{47EC628F-C044-4F20-B62D-21B04E2A5BD3}">
					<States/>
				</StateGroup>
				<StateGroup Id="2730119150" Name="Outdoors" ObjectPath="\States\Default Work Unit\Rooms\Room_Type\Outdoors" GUID="{EA10CE5A-BCC8-4AE8-9177-752CEF2B8D12}">
					<States/>
				</StateGroup>
				<StateGroup Id="3059984139" Name="Tunnel" ObjectPath="\States\Default Work Unit\Rooms\Room_Type\Tunnel" GUID="{F65CF828-F9DE-4675-B6E9-86BC56F7B96F}">
					<States/>
				</StateGroup>
				<StateGroup Id="3791155954" Name="Muted" ObjectPath="\States\Default Work Unit\Music\BoxOpeningStingerState\Muted" GUID="{4D12F6FF-B7BE-42A8-AE76-49832BECE1DA}">
					<States/>
				</StateGroup>
				<StateGroup Id="4174102348" Name="Enabled" ObjectPath="\States\Default Work Unit\Interactions\WorldKeysEnabled\Enabled" GUID="{878828F1-1468-4F40-A5E9-4D39491D6B11}">
					<States/>
				</StateGroup>
			</StateGroups>
			<SwitchGroups>
				<SwitchGroup Id="1458816175" Name="FootstepType" ObjectPath="\Switches\Default Work Unit\FootstepType" GUID="{8274F53A-432D-4B3C-B3B2-7B0DCFA58A47}">
					<Switches>
						<Switch Id="841620460" Name="Concrete" ObjectPath="\Switches\Default Work Unit\FootstepType\Concrete" GUID="{F6050909-D3FC-4A0B-B34B-CED6BB085408}"/>
						<Switch Id="2185786256" Name="Gravel" ObjectPath="\Switches\Default Work Unit\FootstepType\Gravel" GUID="{0DA1C6E4-91C6-467A-A8DC-8C1509316FB7}"/>
						<Switch Id="4248645337" Name="Grass" ObjectPath="\Switches\Default Work Unit\FootstepType\Grass" GUID="{05C16097-8E3C-4946-A103-D61957EBA3B4}"/>
						<Switch Id="446279778" Name="Bed" ObjectPath="\Switches\Default Work Unit\FootstepType\Bed" GUID="{C9ED3BA4-F979-4932-8E3B-C493E6E05FEA}"/>
						<Switch Id="2058049674" Name="Wood" ObjectPath="\Switches\Default Work Unit\FootstepType\Wood" GUID="{1338EB15-8A56-4726-ACE6-2940071E11BB}"/>
						<Switch Id="2473969246" Name="Metal" ObjectPath="\Switches\Default Work Unit\FootstepType\Metal" GUID="{DAC7E030-D095-4C82-90E9-955164EC2CA0}"/>
						<Switch Id="2449969375" Name="Glass" ObjectPath="\Switches\Default Work Unit\FootstepType\Glass" GUID="{6076D9FF-D4F2-4936-AD82-036303957D93}"/>
					</Switches>
				</SwitchGroup>
				<SwitchGroup Id="1468846155" Name="VampFootstep" ObjectPath="\Switches\Default Work Unit\VampFootstep" GUID="{45A5B231-B4A0-422A-8F8A-9C8963BABA9F}">
					<Switches>
						<Switch Id="4174102348" Name="Enabled" ObjectPath="\Switches\Default Work Unit\VampFootstep\Enabled" GUID="{556C6E51-2F20-435E-9A52-BDDC2426B7A9}"/>
						<Switch Id="3248502869" Name="Disabled" ObjectPath="\Switches\Default Work Unit\VampFootstep\Disabled" GUID="{BEAF7BB4-7668-4521-9DD2-723E4A509356}"/>
					</Switches>
				</SwitchGroup>
			</SwitchGroups>
			<Triggers>
				<Trigger Id="556308635" Name="BoxDropStinger" ObjectPath="\Triggers\Default Work Unit\BoxDropStinger"/>
				<Trigger Id="3525814506" Name="BoxPickupStinger" ObjectPath="\Triggers\Default Work Unit\BoxPickupStinger"/>
			</Triggers>
		</SoundBank>
	</SoundBanks>
</SoundBanksInfo>
